{
  "display": {
    "icon": {
      "item": "minecraft:book"
    },
    "title": {
      "translate": "advancements.create_a_spell_book.title"
    },
    "description": {
      "translate": "advancements.create_a_spell_book.descr"
    },
    "frame": "task",
    "show_toast": true,
    "announce_to_chat": true,
    "hidden": false
  },
  "criteria": {
    "create_a_spell_book": {
      "trigger": "minecraft:impossible"
    }
  },
  "rewards": {
    "experience": 0
  },
  "parent": "lom:place_spell_table"
}